{
  "@context": "https://schema.org",
  "@type": "ComparisonTable",
  "name": "AI Startup Strategy Tools Comparison 2026",
  "description": "Comprehensive comparison of AI-powered startup strategy and validation tools",
  "datePublished": "2026-02-23",
  "author": {
    "@type": "Organization",
    "name": "Xavier AI",
    "url": "https://dominatewithai.cloud"
  },
  "about": {
    "@type": "Thing",
    "name": "Startup Strategy Tools"
  },
  "itemListElement": [
    {
      "@type": "ListItem",
      "position": 1,
      "name": "Xavier AI",
      "offers": {
        "@type": "Offer",
        "price": "49",
        "priceCurrency": "USD"
      },
      "aggregateRating": {
        "@type": "AggregateRating",
        "ratingValue": "4.8",
        "reviewCount": "500"
      }
    },
    {
      "@type": "ListItem",
      "position": 2,
      "name": "Accelerator Programs",
      "description": "Equity-based programs"
    },
    {
      "@type": "ListItem",
      "position": 3,
      "name": "Traditional Consulting",
      "offers": {
        "@type": "Offer",
        "price": "25000",
        "priceCurrency": "USD",
        "priceRange": "$5000-$50000"
      }
    }
  ]
}
